[
    {
        "code": "digital-designer-1",
        "name": "Digital Designer 1",
        "subtitle": "Full-Time 1",
        "description": "Lorem ipsum dolor sit amet 1",
        "expected": [
            "Esperamos 7",
            "Esperamos 6",
            "Esperamos 5",
            "Esperamos 4",
            "Esperamos 3",
            "Esperamos 2",
            "Esperamos 1"
        ],
        "bonus": [
            "Bonus 7",
            "Bonus 6",
            "Bonus 5",
            "Bonus 4",
            "Bonus 3",
            "Bonus 2",
            "Bonus 1"
        ]
    },
    {
        "code": "digital-designer-2",
        "name": "Digital Designer 2",
        "subtitle": "Full-Time 2",
        "description": "Lorem ipsum dolor sit amet 2",
        "expected": [
            "Esperamos 7",
            "Esperamos 6",
            "Esperamos 5",
            "Esperamos 4",
            "Esperamos 3",
            "Esperamos 2",
            "Esperamos 1"
        ],
        "bonus": [
            "Bonus 7",
            "Bonus 6",
            "Bonus 5",
            "Bonus 4",
            "Bonus 3",
            "Bonus 2",
            "Bonus 1"
        ]
    },
    {
        "code": "digital-designer-3",
        "name": "Digital Designer 3",
        "subtitle": "Full-Time 3",
        "description": "Lorem ipsum dolor sit amet 3",
        "expected": [
            "Esperamos 7",
            "Esperamos 6",
            "Esperamos 5",
            "Esperamos 4",
            "Esperamos 3",
            "Esperamos 2",
            "Esperamos 1"
        ],
        "bonus": [
            "Bonus 7",
            "Bonus 6",
            "Bonus 5",
            "Bonus 4",
            "Bonus 3",
            "Bonus 2",
            "Bonus 1"
        ]
    },
    {
        "code": "digital-designer-4",
        "name": "Digital Designer 4",
        "subtitle": "Full-Time 4",
        "description": "Lorem ipsum dolor sit amet 4",
        "expected": [
            "Esperamos 7",
            "Esperamos 6",
            "Esperamos 5",
            "Esperamos 4",
            "Esperamos 3",
            "Esperamos 2",
            "Esperamos 1"
        ],
        "bonus": [
            "Bonus 7",
            "Bonus 6",
            "Bonus 5",
            "Bonus 4",
            "Bonus 3",
            "Bonus 2",
            "Bonus 1"
        ]
    },
    {
        "code": "digital-designer-5",
        "name": "Digital Designer 5",
        "subtitle": "Full-Time 5",
        "description": "Lorem ipsum dolor sit amet 5",
        "expected": [
            "Esperamos 7",
            "Esperamos 6",
            "Esperamos 5",
            "Esperamos 4",
            "Esperamos 3",
            "Esperamos 2",
            "Esperamos 1"
        ],
        "bonus": [
            "Bonus 7",
            "Bonus 6",
            "Bonus 5",
            "Bonus 4",
            "Bonus 3",
            "Bonus 2",
            "Bonus 1"
        ]
    },
    {
        "code": "digital-designer-6",
        "name": "Digital Designer 6",
        "subtitle": "Full-Time 6",
        "description": "Lorem ipsum dolor sit amet 6",
        "expected": [
            "Esperamos 7",
            "Esperamos 6",
            "Esperamos 5",
            "Esperamos 4",
            "Esperamos 3",
            "Esperamos 2",
            "Esperamos 1"
        ],
        "bonus": [
            "Bonus 7",
            "Bonus 6",
            "Bonus 5",
            "Bonus 4",
            "Bonus 3",
            "Bonus 2",
            "Bonus 1"
        ]
    }
]